{
    "verion": "3.16.7",
    "flags": {},
    "shapes": [
        [
            {
                "label": "column",
                "line_color": "null",
                "fill_color": "null",
                "points": [
                    [
                        1271.0,
                        405.0
                    ],
                    [
                        1290.0,
                        418.0
                    ]
                ],
                "shape_type": "polygon",
                "flags": {}
            }
        ],
        [
            {
                "label": "column",
                "line_color": "null",
                "fill_color": "null",
                "points": [
                    [
                        864.0,
                        405.0
                    ],
                    [
                        884.0,
                        418.0
                    ]
                ],
                "shape_type": "polygon",
                "flags": {}
            }
        ],
        [
            {
                "label": "column",
                "line_color": "null",
                "fill_color": "null",
                "points": [
                    [
                        613.0,
                        405.0
                    ],
                    [
                        630.0,
                        419.0
                    ]
                ],
                "shape_type": "polygon",
                "flags": {}
            }
        ],
        [
            {
                "label": "column",
                "line_color": "null",
                "fill_color": "null",
                "points": [
                    [
                        1275.0,
                        606.0
                    ],
                    [
                        1290.0,
                        631.0
                    ]
                ],
                "shape_type": "polygon",
                "flags": {}
            }
        ],
        [
            {
                "label": "column",
                "line_color": "null",
                "fill_color": "null",
                "points": [
                    [
                        1352.0,
                        769.0
                    ],
                    [
                        1373.0,
                        783.0
                    ]
                ],
                "shape_type": "polygon",
                "flags": {}
            }
        ],
        [
            {
                "label": "column",
                "line_color": "null",
                "fill_color": "null",
                "points": [
                    [
                        1352.0,
                        985.0
                    ],
                    [
                        1373.0,
                        999.0
                    ]
                ],
                "shape_type": "polygon",
                "flags": {}
            }
        ],
        [
            {
                "label": "column",
                "line_color": "null",
                "fill_color": "null",
                "points": [
                    [
                        950.0,
                        621.0
                    ],
                    [
                        977.0,
                        635.0
                    ]
                ],
                "shape_type": "polygon",
                "flags": {}
            }
        ],
        [
            {
                "label": "column",
                "line_color": "null",
                "fill_color": "null",
                "points": [
                    [
                        950.0,
                        769.0
                    ],
                    [
                        977.0,
                        783.0
                    ]
                ],
                "shape_type": "polygon",
                "flags": {}
            }
        ],
        [
            {
                "label": "column",
                "line_color": "null",
                "fill_color": "null",
                "points": [
                    [
                        947.0,
                        985.0
                    ],
                    [
                        968.0,
                        999.0
                    ]
                ],
                "shape_type": "polygon",
                "flags": {}
            }
        ],
        [
            {
                "label": "column",
                "line_color": "null",
                "fill_color": "null",
                "points": [
                    [
                        374.0,
                        405.0
                    ],
                    [
                        400.0,
                        419.0
                    ]
                ],
                "shape_type": "polygon",
                "flags": {}
            }
        ],
        [
            {
                "label": "column",
                "line_color": "null",
                "fill_color": "null",
                "points": [
                    [
                        111.0,
                        405.0
                    ],
                    [
                        130.0,
                        419.0
                    ]
                ],
                "shape_type": "polygon",
                "flags": {}
            }
        ],
        [
            {
                "label": "column",
                "line_color": "null",
                "fill_color": "null",
                "points": [
                    [
                        111.0,
                        573.0
                    ],
                    [
                        139.0,
                        587.0
                    ]
                ],
                "shape_type": "polygon",
                "flags": {}
            }
        ],
        [
            {
                "label": "column",
                "line_color": "null",
                "fill_color": "null",
                "points": [
                    [
                        391.0,
                        588.0
                    ],
                    [
                        405.0,
                        614.0
                    ]
                ],
                "shape_type": "polygon",
                "flags": {}
            }
        ],
        [
            {
                "label": "column",
                "line_color": "null",
                "fill_color": "null",
                "points": [
                    [
                        616.0,
                        588.0
                    ],
                    [
                        642.0,
                        603.0
                    ]
                ],
                "shape_type": "polygon",
                "flags": {}
            }
        ],
        [
            {
                "label": "column",
                "line_color": "null",
                "fill_color": "null",
                "points": [
                    [
                        784.0,
                        621.0
                    ],
                    [
                        799.0,
                        647.0
                    ]
                ],
                "shape_type": "polygon",
                "flags": {}
            }
        ],
        [
            {
                "label": "column",
                "line_color": "null",
                "fill_color": "null",
                "points": [
                    [
                        784.0,
                        757.0
                    ],
                    [
                        799.0,
                        783.0
                    ]
                ],
                "shape_type": "polygon",
                "flags": {}
            }
        ],
        [
            {
                "label": "column",
                "line_color": "null",
                "fill_color": "null",
                "points": [
                    [
                        390.0,
                        790.0
                    ],
                    [
                        405.0,
                        815.0
                    ]
                ],
                "shape_type": "polygon",
                "flags": {}
            }
        ],
        [
            {
                "label": "column",
                "line_color": "null",
                "fill_color": "null",
                "points": [
                    [
                        702.0,
                        866.0
                    ],
                    [
                        719.0,
                        881.0
                    ]
                ],
                "shape_type": "polygon",
                "flags": {}
            }
        ],
        [
            {
                "label": "column",
                "line_color": "null",
                "fill_color": "null",
                "points": [
                    [
                        616.0,
                        801.0
                    ],
                    [
                        642.0,
                        816.0
                    ]
                ],
                "shape_type": "polygon",
                "flags": {}
            }
        ],
        [
            {
                "label": "column",
                "line_color": "null",
                "fill_color": "null",
                "points": [
                    [
                        111.0,
                        819.0
                    ],
                    [
                        139.0,
                        834.0
                    ]
                ],
                "shape_type": "polygon",
                "flags": {}
            }
        ],
        [
            {
                "label": "column",
                "line_color": "null",
                "fill_color": "null",
                "points": [
                    [
                        695.0,
                        985.0
                    ],
                    [
                        713.0,
                        998.0
                    ]
                ],
                "shape_type": "polygon",
                "flags": {}
            }
        ],
        [
            {
                "label": "column",
                "line_color": "null",
                "fill_color": "null",
                "points": [
                    [
                        426.0,
                        985.0
                    ],
                    [
                        453.0,
                        999.0
                    ]
                ],
                "shape_type": "polygon",
                "flags": {}
            }
        ],
        [
            {
                "label": "column",
                "line_color": "null",
                "fill_color": "null",
                "points": [
                    [
                        112.0,
                        985.0
                    ],
                    [
                        130.0,
                        999.0
                    ]
                ],
                "shape_type": "polygon",
                "flags": {}
            }
        ],
        [
            {
                "label": "beam",
                "line_color": "null",
                "fill_color": "null",
                "points": [
                    [
                        886.0,
                        404.0
                    ],
                    [
                        1270.0,
                        419.0
                    ]
                ],
                "shape_type": "polygon",
                "flags": {}
            }
        ],
        [
            {
                "label": "beam",
                "line_color": "null",
                "fill_color": "null",
                "points": [
                    [
                        1273.0,
                        420.0
                    ],
                    [
                        1293.0,
                        605.0
                    ]
                ],
                "shape_type": "polygon",
                "flags": {}
            }
        ],
        [
            {
                "label": "beam",
                "line_color": "null",
                "fill_color": "null",
                "points": [
                    [
                        863.0,
                        420.0
                    ],
                    [
                        885.0,
                        618.0
                    ]
                ],
                "shape_type": "polygon",
                "flags": {}
            }
        ],
        [
            {
                "label": "beam",
                "line_color": "null",
                "fill_color": "null",
                "points": [
                    [
                        611.0,
                        420.0
                    ],
                    [
                        633.0,
                        587.0
                    ]
                ],
                "shape_type": "polygon",
                "flags": {}
            }
        ],
        [
            {
                "label": "beam",
                "line_color": "null",
                "fill_color": "null",
                "points": [
                    [
                        381.0,
                        419.0
                    ],
                    [
                        404.0,
                        586.0
                    ]
                ],
                "shape_type": "polygon",
                "flags": {}
            }
        ],
        [
            {
                "label": "beam",
                "line_color": "null",
                "fill_color": "null",
                "points": [
                    [
                        111.0,
                        418.0
                    ],
                    [
                        133.0,
                        571.0
                    ]
                ],
                "shape_type": "polygon",
                "flags": {}
            }
        ],
        [
            {
                "label": "beam",
                "line_color": "null",
                "fill_color": "null",
                "points": [
                    [
                        632.0,
                        404.0
                    ],
                    [
                        863.0,
                        419.0
                    ]
                ],
                "shape_type": "polygon",
                "flags": {}
            }
        ],
        [
            {
                "label": "beam",
                "line_color": "null",
                "fill_color": "null",
                "points": [
                    [
                        401.0,
                        404.0
                    ],
                    [
                        612.0,
                        419.0
                    ]
                ],
                "shape_type": "polygon",
                "flags": {}
            }
        ],
        [
            {
                "label": "beam",
                "line_color": "null",
                "fill_color": "null",
                "points": [
                    [
                        132.0,
                        404.0
                    ],
                    [
                        372.0,
                        420.0
                    ]
                ],
                "shape_type": "polygon",
                "flags": {}
            }
        ],
        [
            {
                "label": "beam",
                "line_color": "null",
                "fill_color": "null",
                "points": [
                    [
                        979.0,
                        619.0
                    ],
                    [
                        1272.0,
                        635.0
                    ]
                ],
                "shape_type": "polygon",
                "flags": {}
            }
        ],
        [
            {
                "label": "beam",
                "line_color": "null",
                "fill_color": "null",
                "points": [
                    [
                        979.0,
                        767.0
                    ],
                    [
                        1350.0,
                        784.0
                    ]
                ],
                "shape_type": "polygon",
                "flags": {}
            }
        ],
        [
            {
                "label": "beam",
                "line_color": "null",
                "fill_color": "null",
                "points": [
                    [
                        1274.0,
                        635.0
                    ],
                    [
                        1291.0,
                        768.0
                    ]
                ],
                "shape_type": "polygon",
                "flags": {}
            }
        ],
        [
            {
                "label": "beam",
                "line_color": "null",
                "fill_color": "null",
                "points": [
                    [
                        1352.0,
                        786.0
                    ],
                    [
                        1373.0,
                        983.0
                    ]
                ],
                "shape_type": "polygon",
                "flags": {}
            }
        ],
        [
            {
                "label": "beam",
                "line_color": "null",
                "fill_color": "null",
                "points": [
                    [
                        969.0,
                        983.0
                    ],
                    [
                        1351.0,
                        1000.0
                    ]
                ],
                "shape_type": "polygon",
                "flags": {}
            }
        ],
        [
            {
                "label": "beam",
                "line_color": "null",
                "fill_color": "null",
                "points": [
                    [
                        946.0,
                        785.0
                    ],
                    [
                        969.0,
                        983.0
                    ]
                ],
                "shape_type": "polygon",
                "flags": {}
            }
        ],
        [
            {
                "label": "beam",
                "line_color": "null",
                "fill_color": "null",
                "points": [
                    [
                        801.0,
                        768.0
                    ],
                    [
                        948.0,
                        783.0
                    ]
                ],
                "shape_type": "polygon",
                "flags": {}
            }
        ],
        [
            {
                "label": "beam",
                "line_color": "null",
                "fill_color": "null",
                "points": [
                    [
                        1059.0,
                        636.0
                    ],
                    [
                        1075.0,
                        766.0
                    ]
                ],
                "shape_type": "polygon",
                "flags": {}
            }
        ],
        [
            {
                "label": "beam",
                "line_color": "null",
                "fill_color": "null",
                "points": [
                    [
                        974.0,
                        637.0
                    ],
                    [
                        986.0,
                        768.0
                    ]
                ],
                "shape_type": "polygon",
                "flags": {}
            }
        ],
        [
            {
                "label": "beam",
                "line_color": "null",
                "fill_color": "null",
                "points": [
                    [
                        800.0,
                        617.0
                    ],
                    [
                        948.0,
                        638.0
                    ]
                ],
                "shape_type": "polygon",
                "flags": {}
            }
        ],
        [
            {
                "label": "beam",
                "line_color": "null",
                "fill_color": "null",
                "points": [
                    [
                        849.0,
                        638.0
                    ],
                    [
                        865.0,
                        768.0
                    ]
                ],
                "shape_type": "polygon",
                "flags": {}
            }
        ],
        [
            {
                "label": "beam",
                "line_color": "null",
                "fill_color": "null",
                "points": [
                    [
                        784.0,
                        649.0
                    ],
                    [
                        799.0,
                        755.0
                    ]
                ],
                "shape_type": "polygon",
                "flags": {}
            }
        ],
        [
            {
                "label": "beam",
                "line_color": "null",
                "fill_color": "null",
                "points": [
                    [
                        645.0,
                        588.0
                    ],
                    [
                        798.0,
                        604.0
                    ]
                ],
                "shape_type": "polygon",
                "flags": {}
            }
        ],
        [
            {
                "label": "beam",
                "line_color": "null",
                "fill_color": "null",
                "points": [
                    [
                        629.0,
                        605.0
                    ],
                    [
                        645.0,
                        798.0
                    ]
                ],
                "shape_type": "polygon",
                "flags": {}
            }
        ],
        [
            {
                "label": "beam",
                "line_color": "null",
                "fill_color": "null",
                "points": [
                    [
                        721.0,
                        865.0
                    ],
                    [
                        946.0,
                        882.0
                    ]
                ],
                "shape_type": "polygon",
                "flags": {}
            }
        ],
        [
            {
                "label": "beam",
                "line_color": "null",
                "fill_color": "null",
                "points": [
                    [
                        716.0,
                        984.0
                    ],
                    [
                        945.0,
                        1000.0
                    ]
                ],
                "shape_type": "polygon",
                "flags": {}
            }
        ],
        [
            {
                "label": "beam",
                "line_color": "null",
                "fill_color": "null",
                "points": [
                    [
                        454.0,
                        985.0
                    ],
                    [
                        693.0,
                        1000.0
                    ]
                ],
                "shape_type": "polygon",
                "flags": {}
            }
        ],
        [
            {
                "label": "beam",
                "line_color": "null",
                "fill_color": "null",
                "points": [
                    [
                        131.0,
                        984.0
                    ],
                    [
                        423.0,
                        1000.0
                    ]
                ],
                "shape_type": "polygon",
                "flags": {}
            }
        ],
        [
            {
                "label": "beam",
                "line_color": "null",
                "fill_color": "null",
                "points": [
                    [
                        432.0,
                        820.0
                    ],
                    [
                        453.0,
                        981.0
                    ]
                ],
                "shape_type": "polygon",
                "flags": {}
            }
        ],
        [
            {
                "label": "beam",
                "line_color": "null",
                "fill_color": "null",
                "points": [
                    [
                        407.0,
                        797.0
                    ],
                    [
                        615.0,
                        820.0
                    ]
                ],
                "shape_type": "polygon",
                "flags": {}
            }
        ],
        [
            {
                "label": "beam",
                "line_color": "null",
                "fill_color": "null",
                "points": [
                    [
                        629.0,
                        817.0
                    ],
                    [
                        645.0,
                        983.0
                    ]
                ],
                "shape_type": "polygon",
                "flags": {}
            }
        ],
        [
            {
                "label": "beam",
                "line_color": "null",
                "fill_color": "null",
                "points": [
                    [
                        698.0,
                        882.0
                    ],
                    [
                        720.0,
                        982.0
                    ]
                ],
                "shape_type": "polygon",
                "flags": {}
            }
        ],
        [
            {
                "label": "beam",
                "line_color": "null",
                "fill_color": "null",
                "points": [
                    [
                        645.0,
                        797.0
                    ],
                    [
                        799.0,
                        816.0
                    ]
                ],
                "shape_type": "polygon",
                "flags": {}
            }
        ],
        [
            {
                "label": "beam",
                "line_color": "null",
                "fill_color": "null",
                "points": [
                    [
                        455.0,
                        870.0
                    ],
                    [
                        628.0,
                        884.0
                    ]
                ],
                "shape_type": "polygon",
                "flags": {}
            }
        ],
        [
            {
                "label": "beam",
                "line_color": "null",
                "fill_color": "null",
                "points": [
                    [
                        502.0,
                        602.0
                    ],
                    [
                        519.0,
                        868.0
                    ]
                ],
                "shape_type": "polygon",
                "flags": {}
            }
        ],
        [
            {
                "label": "beam",
                "line_color": "null",
                "fill_color": "null",
                "points": [
                    [
                        407.0,
                        588.0
                    ],
                    [
                        610.0,
                        604.0
                    ]
                ],
                "shape_type": "polygon",
                "flags": {}
            }
        ],
        [
            {
                "label": "beam",
                "line_color": "null",
                "fill_color": "null",
                "points": [
                    [
                        521.0,
                        652.0
                    ],
                    [
                        629.0,
                        669.0
                    ]
                ],
                "shape_type": "polygon",
                "flags": {}
            }
        ],
        [
            {
                "label": "beam",
                "line_color": "null",
                "fill_color": "null",
                "points": [
                    [
                        520.0,
                        747.0
                    ],
                    [
                        628.0,
                        763.0
                    ]
                ],
                "shape_type": "polygon",
                "flags": {}
            }
        ],
        [
            {
                "label": "beam",
                "line_color": "null",
                "fill_color": "null",
                "points": [
                    [
                        390.0,
                        617.0
                    ],
                    [
                        405.0,
                        787.0
                    ]
                ],
                "shape_type": "polygon",
                "flags": {}
            }
        ],
        [
            {
                "label": "beam",
                "line_color": "null",
                "fill_color": "null",
                "points": [
                    [
                        134.0,
                        614.0
                    ],
                    [
                        390.0,
                        630.0
                    ]
                ],
                "shape_type": "polygon",
                "flags": {}
            }
        ],
        [
            {
                "label": "beam",
                "line_color": "null",
                "fill_color": "null",
                "points": [
                    [
                        111.0,
                        590.0
                    ],
                    [
                        134.0,
                        816.0
                    ]
                ],
                "shape_type": "polygon",
                "flags": {}
            }
        ],
        [
            {
                "label": "beam",
                "line_color": "null",
                "fill_color": "null",
                "points": [
                    [
                        111.0,
                        836.0
                    ],
                    [
                        134.0,
                        982.0
                    ]
                ],
                "shape_type": "polygon",
                "flags": {}
            }
        ]
    ],
    "line_color": [
        0,
        255,
        0,
        128
    ],
    "fillColor": [
        255,
        0,
        0,
        128
    ],
    "imagePath": "aug1_EDF 08 - EST-01.jpg",
    "imageData": "",
    "imageHeight": 1280,
    "imageWidth": 1600
}